pypaperless_cli/__init__.py
pypaperless_cli/api.py
pypaperless_cli/app.py
pypaperless_cli/commands/__init__.py
pypaperless_cli/commands/auth.py
pypaperless_cli/commands/document/__init__.py
pypaperless_cli/commands/document/edit.py
pypaperless_cli/commands/document/show.py
pypaperless_cli/config/__init__.py
pypaperless_cli/config/account.py
pypaperless_cli/config/config.py
pypaperless_cli/const.py
pypaperless_cli/py.typed
pypaperless_cli/utils/__init__.py
pypaperless_cli/utils/converters/__init__.py
pypaperless_cli/utils/converters/custom_field.py
pypaperless_cli/utils/converters/helpers/__init__.py
pypaperless_cli/utils/converters/helpers/strtobool.py
pypaperless_cli/utils/converters/tag.py
pypaperless_cli/utils/groups.py
pypaperless_cli/utils/highlighter.py
pypaperless_cli/utils/types.py
pypaperless_cli/utils/validators/__init__.py
pypaperless_cli/utils/validators/custom_field.py
pypaperless_cli/utils/validators/document.py
pypaperless_cli/utils/validators/tag.py
pypaperless_cli-0.3.1.dist-info/LICENSE
pypaperless_cli-0.3.1.dist-info/METADATA
pypaperless_cli-0.3.1.dist-info/WHEEL
pypaperless_cli-0.3.1.dist-info/entry_points.txt
pypaperless_cli-0.3.1.dist-info/RECORD
