Metadata-Version: 2.3
Name: pypaperless-cli
Version: 0.3.1
Summary: 
Author: Marcel Brückner
Author-email: marcelbrueckner@users.noreply.github.com
Requires-Python: >=3.12,<4.0
Classifier: Programming Language :: Python :: 3
Classifier: Programming Language :: Python :: 3.12
Classifier: Programming Language :: Python :: 3.13
Requires-Dist: arrow (>=1.3.0,<2.0.0)
Requires-Dist: cyclopts (>=2.5.0,<3.0.0)
Requires-Dist: httpx (>=0.27.0,<0.28.0)
Requires-Dist: pypaperless (>=4.0.0,<5.0.0)
Requires-Dist: tomlkit (>=0.12.4,<0.13.0)
Requires-Dist: xdg-base-dirs (>=6.0.1,<7.0.0)
